README.md
setup.py
ayewa/__init__.py
ayewa/admin.py
ayewa/apps.py
ayewa/blocks.py
ayewa/models.py
ayewa/tests.py
ayewa/views.py
ayewa.egg-info/PKG-INFO
ayewa.egg-info/SOURCES.txt
ayewa.egg-info/dependency_links.txt
ayewa.egg-info/not-zip-safe
ayewa.egg-info/top_level.txt
ayewa/migrations/0001_initial.py
ayewa/migrations/0002_resource.py
ayewa/migrations/0003_remove_resource_name.py
ayewa/migrations/0004_remove_resource_solution.py
ayewa/migrations/0005_auto_20201016_1641.py
ayewa/migrations/0006_resourceclass.py
ayewa/migrations/0007_resource_resource_class.py
ayewa/migrations/0008_auto_20201017_0824.py
ayewa/migrations/0009_auto_20201017_1115.py
ayewa/migrations/0010_resource_solution.py
ayewa/migrations/0011_resourceindexpage.py
ayewa/migrations/0012_actionapproach_actionapproachindexpage.py
ayewa/migrations/0013_people_role.py
ayewa/migrations/0014_peopleindexpage.py
ayewa/migrations/0015_resource_people.py
ayewa/migrations/0016_otherindexpage_scienceindexpage.py
ayewa/migrations/0017_indexpage_body.py
ayewa/migrations/0018_auto_20201023_1328.py
ayewa/migrations/0019_auto_20201023_1332.py
ayewa/migrations/0020_auto_20201023_1618.py
ayewa/migrations/0021_auto_20201023_1642.py
ayewa/migrations/0022_auto_20201024_1059.py
ayewa/migrations/0023_auto_20201025_1446.py
ayewa/migrations/0024_remove_indexpage_nav_description.py
ayewa/migrations/__init__.py
ayewa/templatetags/__init__.py
ayewa/templatetags/ayewa_tags.py
ayewa/templatetags/gallery_tags.py
ayewa/templatetags/navigation_tags.py