Metadata-Version: 1.0
Name: ayewa
Version: 0.9
Summary: Core Module for Ayewa Application
Home-page: https://github.com/pdbethke/ayewa
Author: siteshell.net
Author-email: pdbethke@siteshell.net
License: LICENSE.txt
Platform: OS Independent
